Metadata-Version: 2.1
Name: package-forkEntropy
Version: 0.2.0
Summary: The implementation and test for the measurement method fork entropy.
Home-page: https://github.com/WuXiangChen/ForkEntropy_ESE
Author: XiangChenWu
Author-email: ixc@smail.nju.edu.cn
Platform: all
Classifier: Programming Language :: Python :: 3
Classifier: License :: OSI Approved :: MIT License
Classifier: Operating System :: OS Independent
Requires-Python: >=3.6
License-File: License
Requires-Dist: numpy
Requires-Dist: pandas
Requires-Dist: json
